unittest_jasmine/__init__.py
unittest_jasmine/_data.py
unittest_jasmine/_info.py
unittest_jasmine/_node.py
unittest_jasmine/_package_manager.py
unittest_jasmine/_runner.py
unittest_jasmine/_setuptools.py
unittest_jasmine/_tb.py
unittest_jasmine/_unittest.py
unittest_jasmine/runner.js
unittest_jasmine-1.0.2.dist-info/DESCRIPTION.rst
unittest_jasmine-1.0.2.dist-info/METADATA
unittest_jasmine-1.0.2.dist-info/RECORD
unittest_jasmine-1.0.2.dist-info/WHEEL
unittest_jasmine-1.0.2.dist-info/metadata.json
unittest_jasmine-1.0.2.dist-info/pbr.json
unittest_jasmine-1.0.2.dist-info/top_level.txt
unittest_jasmine-1.0.2.dist-info/zip-safe
