Metadata-Version: 2.0
Name: unittest-jasmine
Version: 1.0.2
Summary: A unittest test loader for Jasmine tests
Home-page: https://github.com/moses-palmer/unittest-jasmine
Author: Moses Palmér
Author-email: moses.palmer@gmail.com
License: GPLv3
Platform: UNKNOWN
